vcdilog/__init__.py
vcdilog/obj.py
vcdilog/prefect.py
vcdilog/vcdilogintrospect.py
vcdilog-0.3.10.dist-info/WHEEL
vcdilog-0.3.10.dist-info/METADATA
vcdilog-0.3.10.dist-info/RECORD
