Metadata-Version: 2.1
Name: vcdilog
Version: 0.3.10
Summary: best practice low-config python logging
License: Unlicense
Author: Robert Lechte
Author-email: robert.lechte@dpc.vic.gov.au
Requires-Python: >=3.8,<4.0
Classifier: License :: Other/Proprietary License
Classifier: Programming Language :: Python :: 3
Classifier: Programming Language :: Python :: 3.8
Classifier: Programming Language :: Python :: 3.9
Requires-Dist: logging_tree
Requires-Dist: pendulum (>=2.1.2,<3.0.0)
Requires-Dist: python-json-logger
Requires-Dist: pyyaml
